app/__init__.py
app/app.py
appsearch-0.1.4.dist-info/METADATA
appsearch-0.1.4.dist-info/RECORD
appsearch-0.1.4.dist-info/WHEEL
appsearch-0.1.4.dist-info/entry_points.txt
appsearch-0.1.4.dist-info/top_level.txt
