Metadata-Version: 2.1
Name: appsearch
Version: 0.1.4
Summary: A work helper, get app package url for JIRA task
Home-page: http://wangzhizhou@git.sankuai.com/scm/~wangzhizhou/appsearch.git
Author: joker
Author-email: wangzhizhou@meituan.com
License: UNKNOWN
Platform: UNKNOWN
Classifier: Programming Language :: Python :: 2
Classifier: Programming Language :: Python :: 3
Classifier: License :: OSI Approved :: MIT License
Classifier: Operating System :: OS Independent
